README.md
setup.py
src/interactive_judger/__init__.py
src/interactive_judger/built_in_judger.py
src/interactive_judger/conf_generator.py
src/interactive_judger/judge.py
src/interactive_judger/judge_result.py
src/interactive_judger/test_case_loader.py
src/interactive_judger/tester.py
src/interactive_judger_py.egg-info/PKG-INFO
src/interactive_judger_py.egg-info/SOURCES.txt
src/interactive_judger_py.egg-info/dependency_links.txt
src/interactive_judger_py.egg-info/entry_points.txt
src/interactive_judger_py.egg-info/top_level.txt