Metadata-Version: 1.2
Name: interactive-judger-py
Version: 1.0.0
Summary: An interactive program judger for Python3
Home-page: UNKNOWN
Author: AD1024
Author-email: dh63@uw.edu
License: AGPL
Platform: UNKNOWN
Requires-Python: >=3.6.0
